nlstruct/__init__.py
nlstruct/base.py
nlstruct/checkpoint.py
nlstruct/data_utils.py
nlstruct/metrics.py
nlstruct/optimization.py
nlstruct/registry.py
nlstruct/torch_utils.py
nlstruct/datasets/__init__.py
nlstruct/datasets/base.py
nlstruct/datasets/bc5cdr.py
nlstruct/datasets/brat.py
nlstruct/datasets/deft.py
nlstruct/datasets/genia.py
nlstruct/datasets/i2b2_temporal.py
nlstruct/datasets/medic.py
nlstruct/datasets/ncbi.py
nlstruct/datasets/quaero.py
nlstruct/datasets/umls.py
nlstruct/models/__init__.py
nlstruct/models/autoregressive.py
nlstruct/models/bitag.py
nlstruct/models/common.py
nlstruct/models/crf.py
nlstruct/models/ner.py
nlstruct/models/qualification.py
nlstruct/models/qualified_ner.py
nlstruct/recipes/__init__.py
nlstruct/recipes/train_ner.py
nlstruct/recipes/train_qualified_ner.py
nlstruct-0.2.0.dist-info/LICENSE
nlstruct-0.2.0.dist-info/METADATA
nlstruct-0.2.0.dist-info/WHEEL
nlstruct-0.2.0.dist-info/top_level.txt
nlstruct-0.2.0.dist-info/RECORD
