Metadata-Version: 2.1
Name: nlstruct
Version: 0.2.0
Summary: Natural language structuring library
Home-page: https://github.com/percevalw/nlstruct
Author: Perceval Wajsburt
Author-email: perceval.wajsburt@sorbonne-universite.fr
License: MIT
Classifier: Programming Language :: Python :: 3
Classifier: License :: OSI Approved :: MIT License
Classifier: Operating System :: OS Independent
Requires-Python: >=3.6
License-File: LICENSE
Requires-Dist: fire
Requires-Dist: torch (>=1.0.0)
Requires-Dist: numpy
Requires-Dist: einops (>=0.3.0)
Requires-Dist: anyascii (>=0.3.2)
Requires-Dist: transformers (>=4.3.0)
Requires-Dist: tqdm (>=4.56.0)
Requires-Dist: scikit-learn
Requires-Dist: pandas
Requires-Dist: pytorch-lightning (>=1.1.7)
Requires-Dist: torchmetrics (>=0.7.3)
Requires-Dist: rich-logger (>=0.3.1)
Requires-Dist: sentencepiece (>=0.1.95)
Requires-Dist: xxhash (>=2.0.0)
Requires-Dist: regex (>=2020.11.13)
Requires-Dist: parse (>=1.19.0)
